beetsplug/oldestdate.py
beets_oldestdate-1.1.4.dist-info/METADATA
beets_oldestdate-1.1.4.dist-info/WHEEL
beets_oldestdate-1.1.4.dist-info/entry_points.txt
beets_oldestdate-1.1.4.dist-info/licenses/LICENSE
beets_oldestdate-1.1.4.dist-info/RECORD
