Metadata-Version: 2.1
Name: beets-oldestdate
Version: 1.1.4
Summary: Beets plugin that finds oldest possible track recording or release date
Project-URL: Homepage, https://github.com/kernitus/beets-oldestdate
Project-URL: Bug Tracker, https://github.com/kernitus/beets-oldestdate/issues
Author: kernitus
License-File: LICENSE
Classifier: License :: OSI Approved :: MIT License
Classifier: Operating System :: OS Independent
Classifier: Programming Language :: Python :: 3
Requires-Python: >=3.7
Requires-Dist: beets~=1.6
Requires-Dist: mediafile~=0.9
Requires-Dist: musicbrainzngs~=0.7
Requires-Dist: python-dateutil~=2.8
